{"id":65,"token":"apologize","pos":{"tags":[{"id":127,"en_word_id":65,"tag":"Verb","priority":1},{"id":128,"en_word_id":65,"tag":"Infinitive","priority":2},{"id":129,"en_word_id":65,"tag":"PresentTense","priority":3},{"id":130,"en_word_id":65,"tag":"VerbPhrase","priority":4}],"bestPosTag":{"id":127,"en_word_id":65,"tag":"Verb","priority":1}},"metaTags":[{"id":65,"metaKey":"specialEnglish","metaValue":{"referenced_at":"2018-09"}}],"synonyms":[{"synonym_word_id":1136,"token":"say"},{"synonym_word_id":1098,"token":"return"},{"synonym_word_id":1248,"token":"state"},{"synonym_word_id":507,"token":"field"},{"synonym_word_id":1324,"token":"tell"}],"phrases":[],"translate":{"ja":[{"id":70,"token":"謝ります"}]}}