{"token":"attempt","pos":{"tags":[{"id":194,"en_word_id":91,"tag":"Verb","priority":1},{"id":195,"en_word_id":91,"tag":"Infinitive","priority":2},{"id":196,"en_word_id":91,"tag":"PresentTense","priority":3},{"id":197,"en_word_id":91,"tag":"VerbPhrase","priority":4}],"bestPosTag":{"id":194,"en_word_id":91,"tag":"Verb","priority":1}},"metaTags":[{"id":91,"metaKey":"specialEnglish","metaValue":{"referenced_at":"2018-09"}},{"id":1539,"metaKey":"basicEnglish","metaValue":{"type":"relatedPopularMovement","referenced_at":"2018-09"}}],"synonyms":[{"synonym_word_id":1544,"token":"bell"},{"synonym_word_id":1681,"token":"nail"},{"synonym_word_id":204,"token":"catch"},{"synonym_word_id":276,"token":"connect"},{"synonym_word_id":1719,"token":"ring"},{"synonym_word_id":523,"token":"fix"},{"synonym_word_id":1535,"token":"band"},{"synonym_word_id":1354,"token":"tie"},{"synonym_word_id":761,"token":"link"},{"synonym_word_id":1692,"token":"paste"},{"synonym_word_id":440,"token":"enter"},{"synonym_word_id":793,"token":"mark"}],"phrases":[],"translate":{"ja":[{"id":95,"token":"試み"},{"id":1507,"token":"企てる"},{"id":1506,"token":"試みる"}]}}