{"token":"bridge","pos":{"tags":[{"id":369,"en_word_id":165,"tag":"Singular","priority":1},{"id":370,"en_word_id":165,"tag":"Noun","priority":2}],"bestPosTag":{"id":369,"en_word_id":165,"tag":"Singular","priority":1}},"metaTags":[{"id":165,"metaKey":"specialEnglish","metaValue":{"referenced_at":"2018-09"}},{"id":1608,"metaKey":"basicEnglish","metaValue":{"type":"relatedVisionThings","referenced_at":"2018-09"}}],"synonyms":[{"synonym_word_id":1301,"token":"suspend"},{"synonym_word_id":432,"token":"end"},{"synonym_word_id":1259,"token":"stop"},{"synonym_word_id":550,"token":"freeze"}],"phrases":[],"translate":{"ja":[{"id":168,"token":"ブリッジ"},{"id":1607,"token":"橋渡し"},{"id":1606,"token":"橋"}]}}