{"id":302,"token":"create","pos":{"tags":[{"id":730,"en_word_id":302,"tag":"Verb","priority":1},{"id":731,"en_word_id":302,"tag":"Infinitive","priority":2},{"id":732,"en_word_id":302,"tag":"PresentTense","priority":3},{"id":733,"en_word_id":302,"tag":"VerbPhrase","priority":4}],"bestPosTag":{"id":730,"en_word_id":302,"tag":"Verb","priority":1}},"metaTags":[{"id":302,"metaKey":"specialEnglish","metaValue":{"referenced_at":"2018-09"}}],"synonyms":[{"synonym_word_id":930,"token":"paper"},{"synonym_word_id":760,"token":"line"},{"synonym_word_id":1239,"token":"spread"},{"synonym_word_id":1693,"token":"parcel"},{"synonym_word_id":110,"token":"bank"},{"synonym_word_id":162,"token":"bread"},{"synonym_word_id":1582,"token":"coat"},{"synonym_word_id":656,"token":"ice"},{"synonym_word_id":1692,"token":"paste"},{"synonym_word_id":1298,"token":"surround"},{"synonym_word_id":1441,"token":"wash"},{"synonym_word_id":1552,"token":"brush"},{"synonym_word_id":929,"token":"paint"},{"synonym_word_id":1796,"token":"wax"},{"synonym_word_id":628,"token":"hold"},{"synonym_word_id":1617,"token":"feather"},{"synonym_word_id":1254,"token":"steel"},{"synonym_word_id":1714,"token":"roof"},{"synonym_word_id":584,"token":"grass"},{"synonym_word_id":905,"token":"oil"},{"synonym_word_id":1294,"token":"surface"},{"synonym_word_id":1061,"token":"recover"},{"synonym_word_id":405,"token":"dust"},{"synonym_word_id":483,"token":"face"}],"phrases":[],"translate":{"ja":[{"id":304,"token":"作ります"}]}}