{"id":551,"token":"fresh","pos":{"tags":[{"id":1360,"en_word_id":551,"tag":"Comparable","priority":1},{"id":1361,"en_word_id":551,"tag":"Adjective","priority":2}],"bestPosTag":{"id":1360,"en_word_id":551,"tag":"Comparable","priority":1}},"metaTags":[{"id":551,"metaKey":"specialEnglish","metaValue":{"referenced_at":"2018-09"}}],"synonyms":[{"synonym_word_id":548,"token":"free","links":{"basicEnglish":"/word/basic-english/free","specialEnglish":"/word/special-english/free"}},{"synonym_word_id":968,"token":"play","links":{"basicEnglish":"/word/basic-english/play","specialEnglish":"/word/special-english/play"}},{"synonym_word_id":1248,"token":"state","links":{"specialEnglish":"/word/special-english/state"}}],"phrases":[],"translate":{"ja":[{"id":549,"token":"新鮮な"}]}}