{"id":772,"token":"long","pos":{"tags":[{"id":1923,"en_word_id":772,"tag":"Comparable","priority":1},{"id":1924,"en_word_id":772,"tag":"Adjective","priority":2}],"bestPosTag":{"id":1923,"en_word_id":772,"tag":"Comparable","priority":1}},"metaTags":[{"id":772,"metaKey":"specialEnglish","metaValue":{"referenced_at":"2018-09"}},{"id":1895,"metaKey":"basicEnglish","metaValue":{"type":"relatedPopularState","referenced_at":"2018-09"}}],"synonyms":[{"synonym_word_id":493,"token":"far","links":{"basicEnglish":"/word/basic-english/far","specialEnglish":"/word/special-english/far"}},{"synonym_word_id":1267,"token":"stretch","links":{"basicEnglish":"/word/basic-english/stretch","specialEnglish":"/word/special-english/stretch"}},{"synonym_word_id":1310,"token":"tall","links":{"basicEnglish":"/word/basic-english/tall","specialEnglish":"/word/special-english/tall"}}],"phrases":[],"translate":{"ja":[{"id":767,"token":"長いです"},{"id":2113,"token":"長い"}]}}