{"token":"news","pos":{"tags":[{"id":2165,"en_word_id":875,"tag":"Plural","priority":1},{"id":2166,"en_word_id":875,"tag":"Noun","priority":2}],"bestPosTag":{"id":2165,"en_word_id":875,"tag":"Plural","priority":1}},"metaTags":[{"id":875,"metaKey":"specialEnglish","metaValue":{"referenced_at":"2018-09"}},{"id":1987,"metaKey":"basicEnglish","metaValue":{"type":"relatedPopularMovement","referenced_at":"2018-09"}}],"synonyms":[],"phrases":[],"translate":{"ja":[{"id":865,"token":"ニュース"},{"id":2189,"token":"報道"}]}}