{"id":950,"token":"perform","pos":{"tags":[{"id":2323,"en_word_id":950,"tag":"Verb","priority":1},{"id":2324,"en_word_id":950,"tag":"Infinitive","priority":2},{"id":2325,"en_word_id":950,"tag":"PresentTense","priority":3},{"id":2326,"en_word_id":950,"tag":"VerbPhrase","priority":4}],"bestPosTag":{"id":2323,"en_word_id":950,"tag":"Verb","priority":1}},"metaTags":[{"id":950,"metaKey":"specialEnglish","metaValue":{"referenced_at":"2018-09"}}],"synonyms":[],"phrases":[],"translate":{"ja":[{"id":935,"token":"行います"}]}}