{"token":"willing","pos":{"tags":[{"id":3667,"en_word_id":1476,"tag":"Verb","priority":1},{"id":3668,"en_word_id":1476,"tag":"Gerund","priority":2},{"id":3669,"en_word_id":1476,"tag":"PresentTense","priority":3},{"id":3670,"en_word_id":1476,"tag":"VerbPhrase","priority":4}],"bestPosTag":{"id":3667,"en_word_id":1476,"tag":"Verb","priority":1}},"metaTags":[{"id":1476,"metaKey":"specialEnglish","metaValue":{"referenced_at":"2018-09"}}],"synonyms":[{"synonym_word_id":797,"token":"mate"},{"synonym_word_id":1488,"token":"woman"},{"synonym_word_id":937,"token":"partner"}],"phrases":[],"translate":{"ja":[{"id":1431,"token":"喜んで"}]}}