{"token":"end","pos":{"tags":[{"id":1068,"en_word_id":432,"tag":"Verb","priority":1},{"id":1069,"en_word_id":432,"tag":"Infinitive","priority":2},{"id":1070,"en_word_id":432,"tag":"PresentTense","priority":3},{"id":1071,"en_word_id":432,"tag":"VerbPhrase","priority":4}],"bestPosTag":{"id":1068,"en_word_id":432,"tag":"Verb","priority":1}},"metaTags":[{"id":432,"metaKey":"specialEnglish","metaValue":{"referenced_at":"2018-09"}},{"id":1755,"metaKey":"basicEnglish","metaValue":{"type":"relatedPopularMovement","referenced_at":"2018-09"}}],"synonyms":[{"synonym_word_id":233,"token":"clean"},{"synonym_word_id":1468,"token":"white"}],"phrases":[],"translate":{"ja":[{"id":433,"token":"終わり"},{"id":1815,"token":"打ち切る"},{"id":1816,"token":"終える"}]}}