{"id":629,"token":"hole","pos":{"tags":[{"id":1559,"en_word_id":629,"tag":"Singular","priority":1},{"id":1560,"en_word_id":629,"tag":"Noun","priority":2}],"bestPosTag":{"id":1559,"en_word_id":629,"tag":"Singular","priority":1}},"metaTags":[{"id":629,"metaKey":"specialEnglish","metaValue":{"referenced_at":"2018-09"}},{"id":1849,"metaKey":"basicEnglish","metaValue":{"type":"relatedPopularMovement","referenced_at":"2018-09"}}],"synonyms":[{"synonym_word_id":1639,"token":"hook"},{"synonym_word_id":1173,"token":"shell"},{"synonym_word_id":722,"token":"kill"},{"synonym_word_id":276,"token":"connect"},{"synonym_word_id":201,"token":"carry"},{"synonym_word_id":629,"token":"hole"},{"synonym_word_id":1364,"token":"top"},{"synonym_word_id":589,"token":"ground"},{"synonym_word_id":968,"token":"play"},{"synonym_word_id":1179,"token":"shoot"},{"synonym_word_id":1211,"token":"smash"},{"synonym_word_id":1196,"token":"single"},{"synonym_word_id":1024,"token":"pull"},{"synonym_word_id":533,"token":"fly"},{"synonym_word_id":395,"token":"double"},{"synonym_word_id":399,"token":"drive"}],"phrases":[],"translate":{"ja":[{"id":626,"token":"穴"},{"id":2055,"token":"くぼみ"},{"id":2056,"token":"欠点"}]}}