{"id":1227,"token":"sound","pos":{"tags":[{"id":3053,"en_word_id":1227,"tag":"Singular","priority":1},{"id":3054,"en_word_id":1227,"tag":"Noun","priority":2}],"bestPosTag":{"id":3053,"en_word_id":1227,"tag":"Singular","priority":1}},"metaTags":[{"id":1227,"metaKey":"specialEnglish","metaValue":{"referenced_at":"2018-09"}},{"id":2171,"metaKey":"basicEnglish","metaValue":{"type":"relatedPopularMovement","referenced_at":"2018-09"}}],"synonyms":[{"synonym_word_id":264,"token":"complete","links":{"basicEnglish":"/word/basic-english/complete","specialEnglish":"/word/special-english/complete"}},{"synonym_word_id":338,"token":"deep","links":{"basicEnglish":"/word/basic-english/deep","specialEnglish":"/word/special-english/deep"}},{"synonym_word_id":579,"token":"good","links":{"basicEnglish":"/word/basic-english/good","specialEnglish":"/word/special-english/good"}},{"synonym_word_id":1643,"token":"healthy","links":{"basicEnglish":"/word/basic-english/healthy"}},{"synonym_word_id":1054,"token":"reasonable","links":{"specialEnglish":"/word/special-english/reasonable"}},{"synonym_word_id":1127,"token":"safe","links":{"basicEnglish":"/word/basic-english/safe","specialEnglish":"/word/special-english/safe"}},{"synonym_word_id":1221,"token":"solid","links":{"basicEnglish":"/word/basic-english/solid","specialEnglish":"/word/special-english/solid"}},{"synonym_word_id":1269,"token":"strong","links":{"basicEnglish":"/word/basic-english/strong","specialEnglish":"/word/special-english/strong"}}],"phrases":[],"translate":{"ja":[{"id":1196,"token":"音"},{"id":1961,"token":"鳴る"},{"id":1962,"token":"響く"}]}}