{"token":"talk","pos":{"tags":[{"id":3280,"en_word_id":1309,"tag":"Verb","priority":1},{"id":3281,"en_word_id":1309,"tag":"PresentTense","priority":3},{"id":3282,"en_word_id":1309,"tag":"VerbPhrase","priority":4},{"id":3283,"en_word_id":1309,"tag":"Infinitive","priority":2}],"bestPosTag":{"id":3280,"en_word_id":1309,"tag":"Verb","priority":1}},"metaTags":[{"id":1309,"metaKey":"specialEnglish","metaValue":{"referenced_at":"2018-09"}},{"id":2270,"metaKey":"basicEnglish","metaValue":{"type":"relatedPopularMovement","referenced_at":"2018-09"}}],"synonyms":[{"synonym_word_id":1775,"token":"tendency"}],"phrases":[],"translate":{"ja":[{"id":1276,"token":"トーク"},{"id":1199,"token":"話す"},{"id":2501,"token":"演説する"}]}}